{
  "name": "gtsam",
  "version": "4.1.1",
  "description": "GTSAM is a C++ library that implements smoothing and mapping (SAM) in robotics and vision, using Factor Graphs and Bayes Networks as the underlying computing paradigm rather than sparse matrices.",
  "homepage": "https://github.com/borglab/gtsam",
  "dependencies": [
    "boost-assign",
    "boost-chrono",
    "boost-date-time",
    "boost-filesystem",
    "boost-format",
    "boost-graph",
    "boost-program-options",
    "boost-regex",
    "boost-serialization",
    "boost-system",
    "boost-thread",
    "boost-timer",
    "eigen3",
    "metis",
    {
        "name": "vcpkg-cmake",
        "host": true
    },
    {
        "name": "vcpkg-cmake-config",
        "host": true
    }
  ]
}
